django_throttle_requests-0.8.0.dist-info/licenses/LICENSE
throttle/__init__.py
throttle/decorators.py
throttle/exceptions.py
throttle/middleware.py
throttle/models.py
throttle/utils.py
throttle/views.py
throttle/backends/__init__.py
throttle/backends/base.py
throttle/backends/cache.py
throttle/backends/redispy.py
throttle/zones/__init__.py
throttle/zones/remoteip.py
django_throttle_requests-0.8.0.dist-info/METADATA
django_throttle_requests-0.8.0.dist-info/WHEEL
django_throttle_requests-0.8.0.dist-info/top_level.txt
django_throttle_requests-0.8.0.dist-info/RECORD
