Metadata-Version: 2.4
Name: django-throttle-requests
Version: 0.8.0
Summary: A Django framework for application-layer rate limiting
Author-email: Lewis Sobotkiewicz <lewis.sobot@gmail.com>
License-Expression: MIT
Project-URL: Repository, https://github.com/sobotklp/django-throttle-requests
Classifier: Development Status :: 4 - Beta
Classifier: Environment :: Web Environment
Classifier: Framework :: Django
Classifier: Intended Audience :: Developers
Classifier: Operating System :: OS Independent
Classifier: Programming Language :: Python
Classifier: Programming Language :: Python :: Implementation :: PyPy
Classifier: Programming Language :: Python :: 3.10
Classifier: Programming Language :: Python :: 3.11
Classifier: Programming Language :: Python :: 3.12
Classifier: Programming Language :: Python :: 3.13
Classifier: Programming Language :: Python :: 3.14
Classifier: Topic :: Software Development :: Libraries
Classifier: Topic :: Software Development :: Libraries :: Python Modules
Requires-Python: >=3.10
License-File: LICENSE
Requires-Dist: django>=5.2
Dynamic: license-file
